dart/__init__.py
dart/dart.py
dart/exception.py
dart/old.py
dart/order_manager.py
dart/webhook.py
dart/generated/__init__.py
dart/generated/client.py
dart/generated/errors.py
dart/generated/types.py
dart/generated/api/__init__.py
dart/generated/api/attachment/__init__.py
dart/generated/api/attachment/add_task_attachment_from_url.py
dart/generated/api/comment/__init__.py
dart/generated/api/comment/add_task_comment.py
dart/generated/api/comment/list_comments.py
dart/generated/api/config/__init__.py
dart/generated/api/config/get_config.py
dart/generated/api/dartboard/__init__.py
dart/generated/api/dartboard/get_dartboard.py
dart/generated/api/doc/__init__.py
dart/generated/api/doc/create_doc.py
dart/generated/api/doc/delete_doc.py
dart/generated/api/doc/get_doc.py
dart/generated/api/doc/list_docs.py
dart/generated/api/doc/update_doc.py
dart/generated/api/folder/__init__.py
dart/generated/api/folder/get_folder.py
dart/generated/api/help_center_article/__init__.py
dart/generated/api/help_center_article/list_help_center_articles.py
dart/generated/api/skill/__init__.py
dart/generated/api/skill/retrieve_skill_by_title.py
dart/generated/api/task/__init__.py
dart/generated/api/task/add_task_time_tracking.py
dart/generated/api/task/create_task.py
dart/generated/api/task/delete_task.py
dart/generated/api/task/get_task.py
dart/generated/api/task/list_tasks.py
dart/generated/api/task/move_task.py
dart/generated/api/task/update_task.py
dart/generated/api/view/__init__.py
dart/generated/api/view/get_view.py
dart/generated/models/__init__.py
dart/generated/models/attachment.py
dart/generated/models/attachment_create_from_url.py
dart/generated/models/comment.py
dart/generated/models/comment_create.py
dart/generated/models/concise_doc.py
dart/generated/models/concise_task.py
dart/generated/models/concise_task_custom_properties_type_0.py
dart/generated/models/dartboard.py
dart/generated/models/doc.py
dart/generated/models/doc_create.py
dart/generated/models/doc_update.py
dart_tools-0.8.11.dist-info/licenses/LICENSE
dart_tools-0.8.11.dist-info/METADATA
dart_tools-0.8.11.dist-info/WHEEL
dart_tools-0.8.11.dist-info/entry_points.txt
dart_tools-0.8.11.dist-info/top_level.txt
dart_tools-0.8.11.dist-info/RECORD
