Metadata-Version: 2.4
Name: dart-tools
Version: 0.8.11
Summary: The Dart CLI and Python Library
Author-email: Dart <software@dartai.com>
License: MIT License
Project-URL: Homepage, https://www.dartai.com/?nr=1
Project-URL: Web App, https://app.dartai.com/
Project-URL: Help Center, https://help.dartai.com/
Project-URL: Bugs and Features, https://github.com/its-dart/dart-tools-py/issues
Project-URL: Library Source, https://github.com/its-dart/dart-tools-py/
Keywords: dart,cli,projectmanagement,taskmanagement
Classifier: Development Status :: 4 - Beta
Classifier: Environment :: Console
Classifier: Intended Audience :: Developers
Classifier: License :: OSI Approved :: MIT License
Classifier: Natural Language :: English
Classifier: Operating System :: OS Independent
Classifier: Programming Language :: Python
Classifier: Programming Language :: Python :: 3
Classifier: Programming Language :: Python :: 3 :: Only
Classifier: Programming Language :: Python :: 3.9
Classifier: Programming Language :: Python :: 3.10
Classifier: Programming Language :: Python :: 3.11
Classifier: Programming Language :: Python :: 3.12
Classifier: Programming Language :: Python :: 3.13
Classifier: Topic :: Office/Business
Classifier: Topic :: Office/Business :: Groupware
Classifier: Topic :: Office/Business :: Scheduling
Classifier: Topic :: Software Development
Classifier: Topic :: Software Development :: Libraries
Classifier: Topic :: Software Development :: Libraries :: Python Modules
Requires-Python: >=3.9
License-File: LICENSE
Requires-Dist: attrs>=25.3
Requires-Dist: dateparser>=1.2
Requires-Dist: httpx>=0.28
Requires-Dist: pick>=2.4
Requires-Dist: platformdirs>=4.3
Dynamic: license-file
